temp_123_ti_client/__init__.py
temp_123_ti_client/api_client.py
temp_123_ti_client/api_response.py
temp_123_ti_client/configuration.py
temp_123_ti_client/exceptions.py
temp_123_ti_client/py.typed
temp_123_ti_client/rest.py
temp_123_ti_client/api/__init__.py
temp_123_ti_client/api/pet_api.py
temp_123_ti_client/api/store_api.py
temp_123_ti_client/api/user_api.py
temp_123_ti_client/models/__init__.py
temp_123_ti_client/models/address.py
temp_123_ti_client/models/api_response.py
temp_123_ti_client/models/category.py
temp_123_ti_client/models/customer.py
temp_123_ti_client/models/order.py
temp_123_ti_client/models/pet.py
temp_123_ti_client/models/tag.py
temp_123_ti_client/models/user.py
temp_123_ti_client-1.0.0.dist-info/METADATA
temp_123_ti_client-1.0.0.dist-info/WHEEL
temp_123_ti_client-1.0.0.dist-info/top_level.txt
temp_123_ti_client-1.0.0.dist-info/RECORD
